odoo/addons/remove_odoo_enterprise/README.rst
odoo/addons/remove_odoo_enterprise/__init__.py
odoo/addons/remove_odoo_enterprise/__manifest__.py
odoo/addons/remove_odoo_enterprise/data/ir_module_module.xml
odoo/addons/remove_odoo_enterprise/i18n/hr.po
odoo/addons/remove_odoo_enterprise/i18n/remove_odoo_enterprise.pot
odoo/addons/remove_odoo_enterprise/models/__init__.py
odoo/addons/remove_odoo_enterprise/models/res_config_settings.py
odoo/addons/remove_odoo_enterprise/readme/CONTRIBUTORS.rst
odoo/addons/remove_odoo_enterprise/readme/DESCRIPTION.rst
odoo/addons/remove_odoo_enterprise/static/description/icon.png
odoo/addons/remove_odoo_enterprise/static/description/index.html
odoo12_addon_remove_odoo_enterprise-12.0.1.2.0.dist-info/METADATA
odoo12_addon_remove_odoo_enterprise-12.0.1.2.0.dist-info/WHEEL
odoo12_addon_remove_odoo_enterprise-12.0.1.2.0.dist-info/top_level.txt
odoo12_addon_remove_odoo_enterprise-12.0.1.2.0.dist-info/RECORD
