Metadata-Version: 2.1
Name: odoo12-addon-remove-odoo-enterprise
Version: 12.0.1.2.0
Summary: Remove enterprise modules and setting items
Home-page: https://github.com/OCA/server-brand/
Author: Eska, Odoo Community Association (OCA)
Author-email: support@odoo-community.org
License: AGPL-3
Platform: UNKNOWN
Classifier: Programming Language :: Python
Classifier: Framework :: Odoo
Classifier: Framework :: Odoo :: 12.0
Classifier: License :: OSI Approved :: GNU Affero General Public License v3
Requires-Python: >=3.5
Requires-Dist: odoo (<12.1dev,>=12.0a)
